kde_classifier/KDEClassifier.py
kde_classifier/__init__.py
kde_classifier-0.1.0.dist-info/licenses/LICENSE
kde_classifier-0.1.0.dist-info/METADATA
kde_classifier-0.1.0.dist-info/WHEEL
kde_classifier-0.1.0.dist-info/top_level.txt
kde_classifier-0.1.0.dist-info/RECORD
