Metadata-Version: 2.4
Name: kde_classifier
Version: 0.1.0
Summary: Kernel Density Estimation classifier with scikit-learn style API, based on Yang Liu et al. (2020).
Author: Yang Liu, Hongxia He, Zhi-Xiong Xiao, Anquan Ji, Jian Ye, Qifan Sun, Yang Cao, Daniel Grønhaug
License: MIT
Project-URL: Homepage, https://github.com/danielftg/KDEClassifier
Project-URL: Repository, https://github.com/danielftg/KDEClassifier
Classifier: Development Status :: 3 - Alpha
Classifier: Intended Audience :: Science/Research
Classifier: License :: OSI Approved :: MIT License
Classifier: Programming Language :: Python :: 3.9
Classifier: Programming Language :: Python :: 3.10
Classifier: Programming Language :: Python :: 3.11
Classifier: Programming Language :: Python :: 3.12
Classifier: Topic :: Scientific/Engineering :: Artificial Intelligence
Classifier: Topic :: Scientific/Engineering :: Information Analysis
Requires-Python: >=3.9
License-File: LICENSE
Requires-Dist: numpy>=1.26.4
Dynamic: license-file
